pegasus_run.sh
pegasusapp/__init__.py
pegasusapp/main.py
pegasusapp/train.py
pegasusapp/utils.py
pegasusapp-0.2.6.dist-info/entry_points.txt
pegasusapp-0.2.6.dist-info/WHEEL
pegasusapp-0.2.6.dist-info/METADATA
pegasusapp-0.2.6.dist-info/RECORD
