Metadata-Version: 2.1
Name: pegasusapp
Version: 0.2.6
Summary: 
Author: John Ginger
Author-email: john@johnginger.co.uk
Requires-Python: >=3.6,<4.0
Classifier: Programming Language :: Python :: 3
Classifier: Programming Language :: Python :: 3.6
Classifier: Programming Language :: Python :: 3.7
Classifier: Programming Language :: Python :: 3.8
Classifier: Programming Language :: Python :: 3.9
Requires-Dist: boto3 (>=1.15.18,<2.0.0)
Requires-Dist: typer[all] (>=0.1.0,<0.2.0)
